README.rst
setup.py
crypto_strategies.egg-info/PKG-INFO
crypto_strategies.egg-info/SOURCES.txt
crypto_strategies.egg-info/dependency_links.txt
crypto_strategies.egg-info/not-zip-safe
crypto_strategies.egg-info/top_level.txt
foo/__init__.py